i_texts/__init__.py
i_texts/core.py
i_texts/main.py
i_texts/py.typed
i_texts-0.2.0.dist-info/WHEEL
i_texts-0.2.0.dist-info/METADATA
i_texts-0.2.0.dist-info/RECORD
