Metadata-Version: 2.1
Name: i-texts
Version: 0.2.0
License: MIT
Author-email: levch <levchenko.d.a1998@gmail.com>
Requires-Python: >=3.10
Requires-Dist: parsenv>=0.1.3
Requires-Dist: pyyaml>=6.0
